odoo10_addon_cmis-10.0.1.2.0.99.dev2-nspkg.pth
odoo/addons/cmis/README.rst
odoo/addons/cmis/__init__.py
odoo/addons/cmis/__manifest__.py
odoo/addons/cmis/exceptions.py
odoo/addons/cmis/demo/cmis_backend_demo.xml
odoo/addons/cmis/i18n/cmis.pot
odoo/addons/cmis/i18n/de.po
odoo/addons/cmis/i18n/fr.po
odoo/addons/cmis/models/__init__.py
odoo/addons/cmis/models/cmis_backend.py
odoo/addons/cmis/security/cmis_backend.xml
odoo/addons/cmis/static/description/icon.png
odoo/addons/cmis/tests/__init__.py
odoo/addons/cmis/tests/test_cmis_backend.py
odoo/addons/cmis/views/cmis_backend.xml
odoo10_addon_cmis-10.0.1.2.0.99.dev2.dist-info/METADATA
odoo10_addon_cmis-10.0.1.2.0.99.dev2.dist-info/WHEEL
odoo10_addon_cmis-10.0.1.2.0.99.dev2.dist-info/namespace_packages.txt
odoo10_addon_cmis-10.0.1.2.0.99.dev2.dist-info/top_level.txt
odoo10_addon_cmis-10.0.1.2.0.99.dev2.dist-info/RECORD
