Metadata-Version: 2.1
Name: odoo10-addon-cmis
Version: 10.0.1.2.0.99.dev2
Summary: Connect Odoo with a CMIS server
Home-page: https://odoo-community.org/
Author: Savoir-faire Linux, ACSONE SA/NV, Odoo Community Association (OCA)
Author-email: support@odoo-community.org
License: AGPL-3
Platform: UNKNOWN
Classifier: Programming Language :: Python
Classifier: Framework :: Odoo
Classifier: License :: OSI Approved :: GNU Affero General Public License v3
Requires-Python: ~=2.7
Requires-Dist: cmislib
Requires-Dist: httplib2
Requires-Dist: odoo (<10.1dev,>=10.0)
